{"nome":"hivgestantes","ano":2015,"listaCampos":[{"15-19":"0","20-34":"1","35-49":"0","Total":"1","bairro":"Integracao"},{"15-19":"0","20-34":"1","35-49":"0","Total":"1","bairro":"Esmeraldina"},{"15-19":"0","20-34":"0","35-49":"1","Total":"1","bairro":"Sao Quirino"},{"15-19":"0","20-34":"1","35-49":"0","Total":"1","bairro":"Florence"},{"15-19":"0","20-34":"1","35-49":"0","Total":"1","bairro":"Dic I"},{"15-19":"1","20-34":"1","35-49":"0","Total":"2","bairro":"Dic Iii"},{"15-19":"0","20-34":"2","35-49":"0","Total":"2","bairro":"Barao Geraldo"},{"15-19":"0","20-34":"1","35-49":"0","Total":"1","bairro":"Pedro Aquino"},{"15-19":"0","20-34":"0","35-49":"1","Total":"1","bairro":"Ipe"},{"15-19":"0","20-34":"1","35-49":"0","Total":"1","bairro":"Paranapanema"},{"15-19":"0","20-34":"1","35-49":"0","Total":"1","bairro":"Boa Esperanca"},{"15-19":"0","20-34":"1","35-49":"0","Total":"1","bairro":"Campo Belo"},{"15-19":"0","20-34":"1","35-49":"0","Total":"1","bairro":"Fernanda"}]}